{
  "docusaurus-plugin-content-docs": {
    "default": {
      "loadedVersions": [
        {
          "versionName": "current",
          "label": "Next",
          "banner": null,
          "badge": false,
          "noIndex": false,
          "className": "docs-version-current",
          "path": "/docs",
          "tagsPath": "/docs/tags",
          "editUrl": "https://github.com/abelranni/lenguajes-estructurados/tree/main/docs",
          "editUrlLocalized": "https://github.com/abelranni/lenguajes-estructurados/tree/main/i18n/es/docusaurus-plugin-content-docs/current",
          "isLast": true,
          "routePriority": -1,
          "sidebarFilePath": "C:\\ucel\\lenguajes-estructurados\\sidebars.js",
          "contentPath": "C:\\ucel\\lenguajes-estructurados\\docs",
          "contentPathLocalized": "C:\\ucel\\lenguajes-estructurados\\i18n\\es\\docusaurus-plugin-content-docs\\current",
          "docs": [
            {
              "unversionedId": "intro",
              "id": "intro",
              "title": "Tutorial Intro",
              "description": "Introducción a la documentación de la asignatura...",
              "source": "@site/docs/intro.md",
              "sourceDirName": ".",
              "slug": "/intro",
              "permalink": "/docs/intro",
              "draft": false,
              "editUrl": "https://github.com/abelranni/lenguajes-estructurados/tree/main/docs/intro.md",
              "tags": [],
              "version": "current",
              "sidebarPosition": 0,
              "frontMatter": {
                "sidebar_position": 0
              },
              "sidebar": "tutorialSidebar",
              "next": {
                "title": "01 - Introducción",
                "permalink": "/docs/category/01---introducción"
              }
            },
            {
              "unversionedId": "Introduccion/01.01_programacion_estructurada",
              "id": "Introduccion/01.01_programacion_estructurada",
              "title": "01.01 - Programación Estructurada",
              "description": "Introducción",
              "source": "@site/docs/01 - Introduccion/01.01_programacion_estructurada.md",
              "sourceDirName": "01 - Introduccion",
              "slug": "/Introduccion/01.01_programacion_estructurada",
              "permalink": "/docs/Introduccion/01.01_programacion_estructurada",
              "draft": false,
              "editUrl": "https://github.com/abelranni/lenguajes-estructurados/tree/main/docs/01 - Introduccion/01.01_programacion_estructurada.md",
              "tags": [],
              "version": "current",
              "frontMatter": {
                "marp": true,
                "theme": "default",
                "size": 969,
                "paginate": true
              },
              "sidebar": "tutorialSidebar",
              "previous": {
                "title": "01 - Introducción",
                "permalink": "/docs/category/01---introducción"
              },
              "next": {
                "title": "01.02 - Buenas prácticas",
                "permalink": "/docs/Introduccion/01.02_buenas_practicas"
              }
            },
            {
              "unversionedId": "Introduccion/01.02_buenas_practicas",
              "id": "Introduccion/01.02_buenas_practicas",
              "title": "01.02 - Buenas prácticas",
              "description": "Lenguajes Estructurados",
              "source": "@site/docs/01 - Introduccion/01.02_buenas_practicas.md",
              "sourceDirName": "01 - Introduccion",
              "slug": "/Introduccion/01.02_buenas_practicas",
              "permalink": "/docs/Introduccion/01.02_buenas_practicas",
              "draft": false,
              "editUrl": "https://github.com/abelranni/lenguajes-estructurados/tree/main/docs/01 - Introduccion/01.02_buenas_practicas.md",
              "tags": [],
              "version": "current",
              "frontMatter": {
                "marp": true,
                "theme": "default",
                "size": 969,
                "paginate": true
              },
              "sidebar": "tutorialSidebar",
              "previous": {
                "title": "01.01 - Programación Estructurada",
                "permalink": "/docs/Introduccion/01.01_programacion_estructurada"
              },
              "next": {
                "title": "02 - Lenguaje C",
                "permalink": "/docs/category/02---lenguaje-c"
              }
            },
            {
              "unversionedId": "Lenguaje C/02.01_conceptos",
              "id": "Lenguaje C/02.01_conceptos",
              "title": "02.01 - Conceptos Generales",
              "description": "Lenguajes Estructurados",
              "source": "@site/docs/02 - Lenguaje C/02.01_conceptos.md",
              "sourceDirName": "02 - Lenguaje C",
              "slug": "/Lenguaje C/02.01_conceptos",
              "permalink": "/docs/Lenguaje C/02.01_conceptos",
              "draft": false,
              "editUrl": "https://github.com/abelranni/lenguajes-estructurados/tree/main/docs/02 - Lenguaje C/02.01_conceptos.md",
              "tags": [],
              "version": "current",
              "frontMatter": {
                "marp": true,
                "theme": "default",
                "size": 969,
                "paginate": true
              },
              "sidebar": "tutorialSidebar",
              "previous": {
                "title": "02.01.E - Juego de la vida de Conway",
                "permalink": "/docs/Lenguaje C/02.01.E_life_conway"
              },
              "next": {
                "title": "02.02.E - Fractales de Julia",
                "permalink": "/docs/Lenguaje C/02.02.E_fractales_julia"
              }
            },
            {
              "unversionedId": "Lenguaje C/02.01.E_life_conway",
              "id": "Lenguaje C/02.01.E_life_conway",
              "title": "02.01.E - Juego de la vida de Conway",
              "description": "Lenguajes Estructurados",
              "source": "@site/docs/02 - Lenguaje C/02.01.E_life_conway.md",
              "sourceDirName": "02 - Lenguaje C",
              "slug": "/Lenguaje C/02.01.E_life_conway",
              "permalink": "/docs/Lenguaje C/02.01.E_life_conway",
              "draft": false,
              "editUrl": "https://github.com/abelranni/lenguajes-estructurados/tree/main/docs/02 - Lenguaje C/02.01.E_life_conway.md",
              "tags": [],
              "version": "current",
              "frontMatter": {
                "marp": true,
                "theme": "default",
                "size": 969,
                "paginate": true
              },
              "sidebar": "tutorialSidebar",
              "previous": {
                "title": "02 - Lenguaje C",
                "permalink": "/docs/category/02---lenguaje-c"
              },
              "next": {
                "title": "02.01 - Conceptos Generales",
                "permalink": "/docs/Lenguaje C/02.01_conceptos"
              }
            },
            {
              "unversionedId": "Lenguaje C/02.02_estructuras",
              "id": "Lenguaje C/02.02_estructuras",
              "title": "02.02 - Estructuras de datos (struct)",
              "description": "\"# Lenguajes Estructurados",
              "source": "@site/docs/02 - Lenguaje C/02.02_estructuras.md",
              "sourceDirName": "02 - Lenguaje C",
              "slug": "/Lenguaje C/02.02_estructuras",
              "permalink": "/docs/Lenguaje C/02.02_estructuras",
              "draft": false,
              "editUrl": "https://github.com/abelranni/lenguajes-estructurados/tree/main/docs/02 - Lenguaje C/02.02_estructuras.md",
              "tags": [],
              "version": "current",
              "frontMatter": {
                "marp": true,
                "theme": "default",
                "size": 969,
                "paginate": true
              },
              "sidebar": "tutorialSidebar",
              "previous": {
                "title": "02.02.E - Fractales de Julia",
                "permalink": "/docs/Lenguaje C/02.02.E_fractales_julia"
              },
              "next": {
                "title": "02.03 - Punteros",
                "permalink": "/docs/Lenguaje C/02.03_punteros"
              }
            },
            {
              "unversionedId": "Lenguaje C/02.02.E_fractales_julia",
              "id": "Lenguaje C/02.02.E_fractales_julia",
              "title": "02.02.E - Fractales de Julia",
              "description": "Lenguajes Estructurados",
              "source": "@site/docs/02 - Lenguaje C/02.02.E_fractales_julia.md",
              "sourceDirName": "02 - Lenguaje C",
              "slug": "/Lenguaje C/02.02.E_fractales_julia",
              "permalink": "/docs/Lenguaje C/02.02.E_fractales_julia",
              "draft": false,
              "editUrl": "https://github.com/abelranni/lenguajes-estructurados/tree/main/docs/02 - Lenguaje C/02.02.E_fractales_julia.md",
              "tags": [],
              "version": "current",
              "frontMatter": {
                "marp": true,
                "theme": "default",
                "size": 969,
                "paginate": true,
                "math": true
              },
              "sidebar": "tutorialSidebar",
              "previous": {
                "title": "02.01 - Conceptos Generales",
                "permalink": "/docs/Lenguaje C/02.01_conceptos"
              },
              "next": {
                "title": "02.02 - Estructuras de datos (struct)",
                "permalink": "/docs/Lenguaje C/02.02_estructuras"
              }
            },
            {
              "unversionedId": "Lenguaje C/02.03_punteros",
              "id": "Lenguaje C/02.03_punteros",
              "title": "02.03 - Punteros",
              "description": "Lenguajes Estructurados",
              "source": "@site/docs/02 - Lenguaje C/02.03_punteros.md",
              "sourceDirName": "02 - Lenguaje C",
              "slug": "/Lenguaje C/02.03_punteros",
              "permalink": "/docs/Lenguaje C/02.03_punteros",
              "draft": false,
              "editUrl": "https://github.com/abelranni/lenguajes-estructurados/tree/main/docs/02 - Lenguaje C/02.03_punteros.md",
              "tags": [],
              "version": "current",
              "frontMatter": {
                "marp": true,
                "theme": "default",
                "size": 969,
                "paginate": true
              },
              "sidebar": "tutorialSidebar",
              "previous": {
                "title": "02.02 - Estructuras de datos (struct)",
                "permalink": "/docs/Lenguaje C/02.02_estructuras"
              },
              "next": {
                "title": "02.04 - Repaso de conceptos",
                "permalink": "/docs/Lenguaje C/02.04_repaso"
              }
            },
            {
              "unversionedId": "Lenguaje C/02.04_repaso",
              "id": "Lenguaje C/02.04_repaso",
              "title": "02.04 - Repaso de conceptos",
              "description": "Conceptos básicos de C",
              "source": "@site/docs/02 - Lenguaje C/02.04_repaso.md",
              "sourceDirName": "02 - Lenguaje C",
              "slug": "/Lenguaje C/02.04_repaso",
              "permalink": "/docs/Lenguaje C/02.04_repaso",
              "draft": false,
              "editUrl": "https://github.com/abelranni/lenguajes-estructurados/tree/main/docs/02 - Lenguaje C/02.04_repaso.md",
              "tags": [],
              "version": "current",
              "frontMatter": {
                "marp": true,
                "theme": "default",
                "size": 969,
                "paginate": true
              },
              "sidebar": "tutorialSidebar",
              "previous": {
                "title": "02.03 - Punteros",
                "permalink": "/docs/Lenguaje C/02.03_punteros"
              },
              "next": {
                "title": "02.05 - Manejo de memoria",
                "permalink": "/docs/Lenguaje C/02.05_memoria"
              }
            },
            {
              "unversionedId": "Lenguaje C/02.05_memoria",
              "id": "Lenguaje C/02.05_memoria",
              "title": "02.05 - Manejo de memoria",
              "description": "Lenguajes Estructurados",
              "source": "@site/docs/02 - Lenguaje C/02.05_memoria.md",
              "sourceDirName": "02 - Lenguaje C",
              "slug": "/Lenguaje C/02.05_memoria",
              "permalink": "/docs/Lenguaje C/02.05_memoria",
              "draft": false,
              "editUrl": "https://github.com/abelranni/lenguajes-estructurados/tree/main/docs/02 - Lenguaje C/02.05_memoria.md",
              "tags": [],
              "version": "current",
              "frontMatter": {
                "marp": true,
                "theme": "default",
                "size": 969,
                "paginate": true
              },
              "sidebar": "tutorialSidebar",
              "previous": {
                "title": "02.04 - Repaso de conceptos",
                "permalink": "/docs/Lenguaje C/02.04_repaso"
              }
            }
          ],
          "drafts": [],
          "sidebars": {
            "tutorialSidebar": [
              {
                "type": "doc",
                "id": "intro"
              },
              {
                "type": "category",
                "label": "01 - Introducción",
                "collapsible": true,
                "collapsed": true,
                "items": [
                  {
                    "type": "doc",
                    "id": "Introduccion/01.01_programacion_estructurada"
                  },
                  {
                    "type": "doc",
                    "id": "Introduccion/01.02_buenas_practicas"
                  }
                ],
                "link": {
                  "type": "generated-index",
                  "description": "5 minutes to learn the most important Docusaurus concepts.",
                  "slug": "/category/01---introducción",
                  "permalink": "/docs/category/01---introducción"
                }
              },
              {
                "type": "category",
                "label": "02 - Lenguaje C",
                "collapsible": true,
                "collapsed": true,
                "items": [
                  {
                    "type": "doc",
                    "id": "Lenguaje C/02.01.E_life_conway"
                  },
                  {
                    "type": "doc",
                    "id": "Lenguaje C/02.01_conceptos"
                  },
                  {
                    "type": "doc",
                    "id": "Lenguaje C/02.02.E_fractales_julia"
                  },
                  {
                    "type": "doc",
                    "id": "Lenguaje C/02.02_estructuras"
                  },
                  {
                    "type": "doc",
                    "id": "Lenguaje C/02.03_punteros"
                  },
                  {
                    "type": "doc",
                    "id": "Lenguaje C/02.04_repaso"
                  },
                  {
                    "type": "doc",
                    "id": "Lenguaje C/02.05_memoria"
                  }
                ],
                "link": {
                  "type": "generated-index",
                  "description": "5 minutes to learn the most important Docusaurus concepts.",
                  "slug": "/category/02---lenguaje-c",
                  "permalink": "/docs/category/02---lenguaje-c"
                }
              }
            ]
          }
        }
      ]
    }
  },
  "docusaurus-plugin-content-blog": {
    "default": {
      "blogSidebarTitle": "Recent posts",
      "blogPosts": [
        {
          "id": "welcome",
          "metadata": {
            "permalink": "/blog/welcome",
            "editUrl": "https://github.com/abelranni/lenguajes-estructurados/tree/main/blog/2023-04-10-bienvenida/index.md",
            "source": "@site/blog/2023-04-10-bienvenida/index.md",
            "title": "Bienvenida",
            "description": "Las funciones de blogging de Docusaurus funcionan con el plugin de blog.",
            "date": "2023-04-10T00:00:00.000Z",
            "formattedDate": "10 de abril de 2023",
            "tags": [
              {
                "label": "lenguajes",
                "permalink": "/blog/tags/lenguajes"
              },
              {
                "label": "c",
                "permalink": "/blog/tags/c"
              },
              {
                "label": "intro",
                "permalink": "/blog/tags/intro"
              }
            ],
            "readingTime": 0.28,
            "hasTruncateMarker": false,
            "authors": [
              {
                "name": "Abel Ranni",
                "title": "Developer",
                "url": "https://github.com/abelranni",
                "imageURL": "https://avatars.githubusercontent.com/u/13169667?v=4",
                "key": "abel"
              }
            ],
            "frontMatter": {
              "slug": "welcome",
              "title": "Bienvenida",
              "authors": [
                "abel"
              ],
              "tags": [
                "lenguajes",
                "c",
                "intro"
              ]
            }
          },
          "content": "Las [funciones de blogging de Docusaurus](https://docusaurus.io/docs/blog) funcionan con el [plugin de blog](https://docusaurus.io/docs/api/plugins/@docusaurus/plugin-content-blog).\n\nSimplemente añada archivos Markdown (o carpetas) al directorio `blog`.\n\nLos autores habituales del blog pueden añadirse a `authors.yml`.\n\nLa fecha de la entrada del blog se puede extraer de los nombres de archivo, tales como:\n\n- `2019-05-30-bienvenida.md`\n- `2019-05-30-welcome/index.md`\n\nEl blog también admite etiquetas."
        }
      ],
      "blogListPaginated": [
        {
          "items": [
            "welcome"
          ],
          "metadata": {
            "permalink": "/blog",
            "page": 1,
            "postsPerPage": 10,
            "totalPages": 1,
            "totalCount": 1,
            "blogDescription": "Blog",
            "blogTitle": "Blog"
          }
        }
      ],
      "blogTags": {
        "/blog/tags/lenguajes": {
          "label": "lenguajes",
          "items": [
            "welcome"
          ],
          "permalink": "/blog/tags/lenguajes",
          "pages": [
            {
              "items": [
                "welcome"
              ],
              "metadata": {
                "permalink": "/blog/tags/lenguajes",
                "page": 1,
                "postsPerPage": 10,
                "totalPages": 1,
                "totalCount": 1,
                "blogDescription": "Blog",
                "blogTitle": "Blog"
              }
            }
          ]
        },
        "/blog/tags/c": {
          "label": "c",
          "items": [
            "welcome"
          ],
          "permalink": "/blog/tags/c",
          "pages": [
            {
              "items": [
                "welcome"
              ],
              "metadata": {
                "permalink": "/blog/tags/c",
                "page": 1,
                "postsPerPage": 10,
                "totalPages": 1,
                "totalCount": 1,
                "blogDescription": "Blog",
                "blogTitle": "Blog"
              }
            }
          ]
        },
        "/blog/tags/intro": {
          "label": "intro",
          "items": [
            "welcome"
          ],
          "permalink": "/blog/tags/intro",
          "pages": [
            {
              "items": [
                "welcome"
              ],
              "metadata": {
                "permalink": "/blog/tags/intro",
                "page": 1,
                "postsPerPage": 10,
                "totalPages": 1,
                "totalCount": 1,
                "blogDescription": "Blog",
                "blogTitle": "Blog"
              }
            }
          ]
        }
      },
      "blogTagsListPath": "/blog/tags"
    }
  },
  "docusaurus-plugin-content-pages": {
    "default": [
      {
        "type": "jsx",
        "permalink": "/",
        "source": "@site/src/pages/index.js"
      },
      {
        "type": "mdx",
        "permalink": "/markdown-page",
        "source": "@site/src/pages/markdown-page.md",
        "title": "Markdown page example",
        "description": "You don't need React to write simple standalone pages.",
        "frontMatter": {
          "title": "Markdown page example"
        }
      }
    ]
  },
  "docusaurus-plugin-debug": {},
  "docusaurus-theme-classic": {},
  "docusaurus-bootstrap-plugin": {},
  "docusaurus-mdx-fallback-plugin": {}
}